truthbench/__init__.py
truthbench/cli.py
truthbench/llms/__init__.py
truthbench/llms/openai.py
truthbench/models.py
truthbench/pipeline.py
truthbench/readers/__init__.py
truthbench/readers/json_reader.py
truthbench/steps/__init__.py
truthbench/steps/blacklist.py
truthbench/steps/counter.py
truthbench/steps/factual.py
truthbench/steps/filter.py
truthbench/steps/noise.py
truthbench/steps/paraphrase.py
truthbench/steps/rank.py
truthbench/tmp.py
truthbench/truth_pipeline.py
truthbench-0.3.0.dist-info/METADATA
truthbench-0.3.0.dist-info/WHEEL
truthbench-0.3.0.dist-info/entry_points.txt
truthbench-0.3.0.dist-info/RECORD
