Metadata-Version: 2.1
Name: truthbench
Version: 0.3.0
Summary: A pipeline-based framework to evaluate factual consistency metrics.
License: MIT
Keywords: nlp,factuality,evaluation,llm,spacy,hallucination,truthfulness,benchmark
Author: Giovanni Gatti Pinheiro
Author-email: giovanni.gatti.pinheiro@gmail.com
Requires-Python: >=3.10,<3.14
Classifier: Development Status :: 4 - Beta
Classifier: Intended Audience :: Developers
Classifier: Intended Audience :: Science/Research
Classifier: License :: OSI Approved :: MIT License
Classifier: Operating System :: OS Independent
Classifier: Programming Language :: Python :: 3
Classifier: Programming Language :: Python :: 3.10
Classifier: Programming Language :: Python :: 3.11
Classifier: Programming Language :: Python :: 3.12
Classifier: Programming Language :: Python :: 3.13
Classifier: Topic :: Scientific/Engineering
Classifier: Topic :: Scientific/Engineering :: Artificial Intelligence
Classifier: Topic :: Scientific/Engineering :: Information Analysis
Classifier: Topic :: Software Development :: Libraries :: Python Modules
Classifier: Topic :: Text Processing :: Linguistic
Provides-Extra: openai
Requires-Dist: openai (>=1.82.0,<2.0.0) ; extra == "openai"
Requires-Dist: spacy (>=3.8.7,<4.0.0)
